.hgignore
.installed.cfg
.project
.pydevproject
LICENSE
MANIFEST.in
README.txt
bootstrap.py
buildout.cfg
setup.py
bin/buildout
docs/HISTORY.txt
docs/README.txt
src/ztfy/__init__.py
src/ztfy.i18n.egg-info/PKG-INFO
src/ztfy.i18n.egg-info/SOURCES.txt
src/ztfy.i18n.egg-info/dependency_links.txt
src/ztfy.i18n.egg-info/entry_points.txt
src/ztfy.i18n.egg-info/namespace_packages.txt
src/ztfy.i18n.egg-info/not-zip-safe
src/ztfy.i18n.egg-info/requires.txt
src/ztfy.i18n.egg-info/top_level.txt
src/ztfy/i18n/README.txt
src/ztfy/i18n/__init__.py
src/ztfy/i18n/adapter.py
src/ztfy/i18n/configure.zcml
src/ztfy/i18n/events.py
src/ztfy/i18n/index.py
src/ztfy/i18n/languages.py
src/ztfy/i18n/metas.py
src/ztfy/i18n/property.py
src/ztfy/i18n/schema.py
src/ztfy/i18n/vocabulary.py
src/ztfy/i18n/browser/__init__.py
src/ztfy/i18n/browser/adapter.py
src/ztfy/i18n/browser/configure.zcml
src/ztfy/i18n/browser/i18n.py
src/ztfy/i18n/browser/namespace.py
src/ztfy/i18n/browser/viewlet.py
src/ztfy/i18n/browser/resources/css/ztfy.i18n.css
src/ztfy/i18n/browser/resources/css/ztfy.i18n.min.css
src/ztfy/i18n/browser/resources/img/tab_bg.gif
src/ztfy/i18n/browser/resources/img/tab_end.gif
src/ztfy/i18n/browser/resources/img/tab_sel_bg.gif
src/ztfy/i18n/browser/resources/img/tab_sel_end.gif
src/ztfy/i18n/browser/resources/img/tabs_bg.gif
src/ztfy/i18n/browser/resources/img/transpose.png
src/ztfy/i18n/browser/resources/img/flags/aa_ET.png
src/ztfy/i18n/browser/resources/img/flags/ab_GE.png
src/ztfy/i18n/browser/resources/img/flags/ae_IR.png
src/ztfy/i18n/browser/resources/img/flags/af_ZA.png
src/ztfy/i18n/browser/resources/img/flags/ak_GH.png
src/ztfy/i18n/browser/resources/img/flags/am_ET.png
src/ztfy/i18n/browser/resources/img/flags/an_ES.png
src/ztfy/i18n/browser/resources/img/flags/ar.png
src/ztfy/i18n/browser/resources/img/flags/ar_AE.png
src/ztfy/i18n/browser/resources/img/flags/ar_BH.png
src/ztfy/i18n/browser/resources/img/flags/ar_DZ.png
src/ztfy/i18n/browser/resources/img/flags/ar_EG.png
src/ztfy/i18n/browser/resources/img/flags/ar_IQ.png
src/ztfy/i18n/browser/resources/img/flags/ar_JO.png
src/ztfy/i18n/browser/resources/img/flags/ar_KW.png
src/ztfy/i18n/browser/resources/img/flags/ar_LB.png
src/ztfy/i18n/browser/resources/img/flags/ar_LY.png
src/ztfy/i18n/browser/resources/img/flags/ar_MA.png
