Metadata-Version: 1.1
Name: ztfy.i18n
Version: 0.3.4
Summary: ZTFY i18n management package for Zope3
Home-page: http://www.ztfy.org
Author: Thierry Florac
Author-email: tflorac@ulthar.net
License: ZPL
Keywords: ZTFY Zope3 I18n
Platform: UNKNOWN
Classifier: License :: OSI Approved :: Zope Public License
Classifier: Development Status :: 4 - Beta
Classifier: Programming Language :: Python
Classifier: Framework :: Zope3
Classifier: Topic :: Software Development :: Libraries :: Python Modules
